README.rst
setup.py
Keno.egg-info/PKG-INFO
Keno.egg-info/SOURCES.txt
Keno.egg-info/dependency_links.txt
Keno.egg-info/requires.txt
Keno.egg-info/top_level.txt
keno/Keno.py
keno/__init__.py