Metadata-Version: 1.1
Name: Keno
Version: 1.2.2
Summary: A Keno Game for Python
Home-page: https://github.com/Xtarii/KenoPython
Author: Lord Alvin Hansen
Author-email: alvin.hansen@elev.ga.ntig.se
License: BSD 2-clause
Platform: UNKNOWN
Classifier: Development Status :: 1 - Planning
Classifier: Intended Audience :: Science/Research
Classifier: License :: OSI Approved :: BSD License
Classifier: Operating System :: POSIX :: Linux
Classifier: Programming Language :: Python :: 3
Classifier: Programming Language :: Python :: 3.4
Classifier: Programming Language :: Python :: 3.5
